{
    "used": {
        "_:id2": {
            "prov:activity": "log:ad4c67b5a-a2af-4eb3-95b4-57ff0ea2c1df",
            "prov:time": "2016-04-13T17:43:19.220478",
            "prov:entity": "bdp:wc8w-nujj"
        }
    },
    "prefix": {
        "ont": "http://datamechanics.io/ontology#",
        "dat": "http://datamechanics.io/data/jlam17_mckay678/",
        "alg": "http://datamechanics.io/algorithm/jlam17_mckay678/",
        "bdp": "https://data.cityofboston.gov/resource/",
        "log": "http://datamechanics.io/log#"
    },
    "wasGeneratedBy": {
        "_:id4": {
            "prov:activity": "log:ad4c67b5a-a2af-4eb3-95b4-57ff0ea2c1df",
            "prov:time": "2016-04-13T17:43:22.001121",
            "prov:entity": "dat:foodEst"
        },
        "_:id13": {
            "prov:activity": "log:ad4c67b5a-a2af-4eb3-95b4-57ff0ea2c1df",
            "prov:time": "2016-04-13T17:43:22.001121",
            "prov:entity": "dat:retailBakery"
        },
        "_:id10": {
            "prov:activity": "log:ad4c67b5a-a2af-4eb3-95b4-57ff0ea2c1df",
            "prov:time": "2016-04-13T17:43:22.001121",
            "prov:entity": "dat:foodPantry"
        },
        "_:id7": {
            "prov:activity": "log:ad4c67b5a-a2af-4eb3-95b4-57ff0ea2c1df",
            "prov:time": "2016-04-13T17:43:22.001121",
            "prov:entity": "dat:cornerStore"
        }
    },
    "wasAssociatedWith": {
        "_:id1": {
            "prov:activity": "log:ad4c67b5a-a2af-4eb3-95b4-57ff0ea2c1df",
            "prov:agent": "alg:foodLocations"
        }
    },
    "entity": {
        "dat:cornerStore": {
            "prov:label": "cornerStore",
            "prov:type": "ont:DataSet"
        },
        "dat:foodPantry": {
            "prov:label": "foodPantry",
            "prov:type": "ont:DataSet"
        },
        "bdp:wc8w-nujj": {
            "prov:label": "Active Food Establishment Licenses",
            "prov:type": "ont:DataResource",
            "ont:Extension": "json"
        },
        "dat:retailBakery": {
            "prov:label": "retailBakery",
            "prov:type": "ont:DataSet"
        },
        "dat:foodEst": {
            "prov:label": "foodEst",
            "prov:type": "ont:DataSet"
        }
    },
    "activity": {
        "log:ad4c67b5a-a2af-4eb3-95b4-57ff0ea2c1df": {
            "prov:endTime": "2016-04-13T17:43:22.001121",
            "prov:type": "ont:Computation",
            "ont:Query": "?accessType=DOWNLOAD",
            "prov:startTime": "2016-04-13T17:43:19.220478"
        }
    },
    "agent": {
        "alg:foodLocations": {
            "prov:type": {
                "$": "prov:SoftwareAgent",
                "type": "prov:QUALIFIED_NAME"
            },
            "ont:Extension": "py"
        }
    },
    "wasDerivedFrom": {
        "_:id14": {
            "prov:activity": "log:ad4c67b5a-a2af-4eb3-95b4-57ff0ea2c1df",
            "prov:usage": "log:ad4c67b5a-a2af-4eb3-95b4-57ff0ea2c1df",
            "prov:generatedEntity": "dat:retailBakery",
            "prov:usedEntity": "bdp:wc8w-nujj",
            "prov:generation": "log:ad4c67b5a-a2af-4eb3-95b4-57ff0ea2c1df"
        },
        "_:id5": {
            "prov:activity": "log:ad4c67b5a-a2af-4eb3-95b4-57ff0ea2c1df",
            "prov:usage": "log:ad4c67b5a-a2af-4eb3-95b4-57ff0ea2c1df",
            "prov:generatedEntity": "dat:foodEst",
            "prov:usedEntity": "bdp:wc8w-nujj",
            "prov:generation": "log:ad4c67b5a-a2af-4eb3-95b4-57ff0ea2c1df"
        },
        "_:id11": {
            "prov:activity": "log:ad4c67b5a-a2af-4eb3-95b4-57ff0ea2c1df",
            "prov:usage": "log:ad4c67b5a-a2af-4eb3-95b4-57ff0ea2c1df",
            "prov:generatedEntity": "dat:foodPantry",
            "prov:usedEntity": "bdp:wc8w-nujj",
            "prov:generation": "log:ad4c67b5a-a2af-4eb3-95b4-57ff0ea2c1df"
        },
        "_:id8": {
            "prov:activity": "log:ad4c67b5a-a2af-4eb3-95b4-57ff0ea2c1df",
            "prov:usage": "log:ad4c67b5a-a2af-4eb3-95b4-57ff0ea2c1df",
            "prov:generatedEntity": "dat:cornerStore",
            "prov:usedEntity": "bdp:wc8w-nujj",
            "prov:generation": "log:ad4c67b5a-a2af-4eb3-95b4-57ff0ea2c1df"
        }
    },
    "wasAttributedTo": {
        "_:id3": {
            "prov:agent": "alg:foodLocations",
            "prov:entity": "dat:foodEst"
        },
        "_:id6": {
            "prov:agent": "alg:foodLocations",
            "prov:entity": "dat:cornerStore"
        },
        "_:id12": {
            "prov:agent": "alg:foodLocations",
            "prov:entity": "dat:retailBakery"
        },
        "_:id9": {
            "prov:agent": "alg:foodLocations",
            "prov:entity": "dat:foodPantry"
        }
    }
}